[{"id":1,"src":"./photos/2_23.jpg","title":"Английский язык","text":"Репетиторы по английскому языку!"},{"id":2,"src":"./photos/2_24.jpg","title":"Математика","text":"Репетиторы по математике!"},{"id":3,"src":"./photos/2_25.jpg","title":"География","text":"Я сдал последний экзамен!"},{"id":4,"src":"https://i.pinimg.com/originals/c9/ea/65/c9ea654eb3a7398b1f702c758c1c4206.jpg","title":"Новый предмет 4","text":"Описание для нового предмета 4"},{"id":5,"src":"https://i.pinimg.com/originals/c9/ea/65/c9ea654eb3a7398b1f702c758c1c4206.jpg","title":"Новый предмет 5","text":"Описание для нового предмета 5"}]